setup.py
Bi_Gau_distributions/Binomialdistribution.py
Bi_Gau_distributions/Gaussiandistribution.py
Bi_Gau_distributions/Generaldistribution.py
Bi_Gau_distributions/__init__.py
Bi_Gau_distributions.egg-info/PKG-INFO
Bi_Gau_distributions.egg-info/SOURCES.txt
Bi_Gau_distributions.egg-info/dependency_links.txt
Bi_Gau_distributions.egg-info/not-zip-safe
Bi_Gau_distributions.egg-info/top_level.txt