Metadata-Version: 1.0
Name: Bi-Gau-distributions
Version: 0.1
Summary: discrete variable probability distribution
Home-page: UNKNOWN
Author: UNKNOWN
Author-email: UNKNOWN
License: UNKNOWN
Platform: UNKNOWN
